{"v":"5.12.1","fr":20,"ip":0,"op":70,"w":309,"h":341,"nm":"金币","ddd":0,"assets":[{"id":"image_0","w":67,"h":72,"u":"images/","p":"img_0.png","e":0},{"id":"image_1","w":61,"h":69,"u":"images/","p":"img_1.png","e":0},{"id":"image_2","w":72,"h":68,"u":"images/","p":"img_2.png","e":0},{"id":"image_3","w":69,"h":44,"u":"images/","p":"img_3.png","e":0},{"id":"image_4","w":62,"h":42,"u":"images/","p":"img_4.png","e":0},{"id":"image_5","w":69,"h":45,"u":"images/","p":"img_5.png","e":0},{"id":"image_6","w":66,"h":23,"u":"images/","p":"img_6.png","e":0},{"id":"image_7","w":66,"h":24,"u":"images/","p":"img_7.png","e":0},{"id":"image_8","w":43,"h":13,"u":"images/","p":"img_8.png","e":0},{"id":"image_9","w":55,"h":36,"u":"images/","p":"img_9.png","e":0},{"id":"image_10","w":204,"h":148,"u":"images/","p":"img_10.jpg","e":0}],"layers":[{"ddd":0,"ind":2,"ty":2,"nm":"金币-右侧","refId":"image_0","sr":1,"ks":{"o":{"a":0,"k":100,"ix":11},"r":{"a":1,"k":[{"i":{"x":[0.764],"y":[1.009]},"o":{"x":[0.469],"y":[0]},"t":0,"s":[-67],"e":[-6.58]},{"i":{"x":[0.597],"y":[0.988]},"o":{"x":[0.177],"y":[0.005]},"t":6,"s":[-6.58],"e":[4]},{"i":{"x":[0.516],"y":[1]},"o":{"x":[0.488],"y":[-0.046]},"t":11,"s":[4],"e":[0]},{"t":17}],"ix":10},"p":{"a":1,"k":[{"i":{"x":0.375,"y":1},"o":{"x":0.662,"y":0},"t":0,"s":[174,39,0],"e":[170.625,217,0],"to":[0,0,0],"ti":[0,0,0]},{"i":{"x":0.375,"y":1},"o":{"x":0,"y":0},"t":6,"s":[170.625,217,0],"e":[172.688,213.875,0],"to":[0,0,0],"ti":[-1.75,-0.25,0]},{"i":{"x":0.375,"y":1},"o":{"x":0.488,"y":0},"t":11,"s":[172.688,213.875,0],"e":[174,217,0],"to":[1.75,0.25,0],"ti":[0,0,0]},{"t":16}],"ix":2,"l":2},"a":{"a":0,"k":[33.5,36,0],"ix":1,"l":2},"s":{"a":0,"k":[100,100,100],"ix":6,"l":2}},"ao":0,"ip":0,"op":1107,"st":-16,"bm":0},{"ddd":0,"ind":3,"ty":2,"nm":"金币-左侧","refId":"image_1","sr":1,"ks":{"o":{"a":0,"k":100,"ix":11},"r":{"a":1,"k":[{"i":{"x":[0.722],"y":[0.963]},"o":{"x":[0.395],"y":[0]},"t":5,"s":[56],"e":[5]},{"i":{"x":[0.645],"y":[0.745]},"o":{"x":[0.376],"y":[0]},"t":11,"s":[5],"e":[-3]},{"i":{"x":[0.588],"y":[1]},"o":{"x":[0.274],"y":[-0.526]},"t":16,"s":[-3],"e":[0]},{"t":21}],"ix":10},"p":{"a":1,"k":[{"i":{"x":0.375,"y":1},"o":{"x":0.662,"y":0},"t":5,"s":[78.5,45.5,0],"e":[76.375,236.875,0],"to":[0,0,0],"ti":[0,0,0]},{"i":{"x":0.104,"y":1},"o":{"x":0.211,"y":0.444},"t":11,"s":[76.375,236.875,0],"e":[77.938,235.062,0],"to":[0,0,0],"ti":[-1.312,-0.312,0]},{"i":{"x":0.375,"y":1},"o":{"x":0.333,"y":0},"t":16,"s":[77.938,235.062,0],"e":[78.5,237.5,0],"to":[1.312,0.312,0],"ti":[0,0,0]},{"t":20}],"ix":2,"l":2},"a":{"a":0,"k":[38.736,59.955,0],"ix":1,"l":2},"s":{"a":0,"k":[100,100,100],"ix":6,"l":2}},"ao":0,"ip":3,"op":1114,"st":-9,"bm":0},{"ddd":0,"ind":4,"ty":2,"nm":"阴影4","refId":"image_2","sr":1,"ks":{"o":{"a":1,"k":[{"i":{"x":[0.667],"y":[1]},"o":{"x":[0.333],"y":[0]},"t":6,"s":[0],"e":[100]},{"t":16}],"ix":11},"r":{"a":0,"k":0,"ix":10},"p":{"a":0,"k":[120.5,211,0],"ix":2,"l":2},"a":{"a":0,"k":[36,34,0],"ix":1,"l":2},"s":{"a":0,"k":[100,100,100],"ix":6,"l":2}},"ao":0,"ip":1,"op":1112,"st":-11,"bm":0},{"ddd":0,"ind":5,"ty":2,"nm":"金币-上","refId":"image_3","sr":1,"ks":{"o":{"a":0,"k":100,"ix":11},"r":{"a":0,"k":0,"ix":10},"p":{"a":1,"k":[{"i":{"x":0.375,"y":1},"o":{"x":0.662,"y":0},"t":5,"s":[132,31,0],"e":[132,150,0],"to":[0,0,0],"ti":[0,0,0]},{"i":{"x":0.375,"y":1},"o":{"x":0.033,"y":0},"t":11,"s":[132,150,0],"e":[132,142.5,0],"to":[0,0,0],"ti":[0,0,0]},{"i":{"x":0.375,"y":1},"o":{"x":0.535,"y":0},"t":16,"s":[132,142.5,0],"e":[132,150,0],"to":[0,0,0],"ti":[0,0,0]},{"t":22}],"ix":2,"l":2},"a":{"a":0,"k":[34.5,22,0],"ix":1,"l":2},"s":{"a":0,"k":[100,100,100],"ix":6,"l":2}},"ao":0,"ip":1,"op":1112,"st":-11,"bm":0},{"ddd":0,"ind":6,"ty":2,"nm":"阴影3","parent":5,"refId":"image_4","sr":1,"ks":{"o":{"a":0,"k":100,"ix":11},"r":{"a":0,"k":0,"ix":10},"p":{"a":0,"k":[29,45,0],"ix":2,"l":2},"a":{"a":0,"k":[31,21,0],"ix":1,"l":2},"s":{"a":0,"k":[100,100,100],"ix":6,"l":2}},"ao":0,"ip":1,"op":1112,"st":-11,"bm":0},{"ddd":0,"ind":7,"ty":2,"nm":"金币-下","refId":"image_5","sr":1,"ks":{"o":{"a":0,"k":100,"ix":11},"r":{"a":0,"k":0,"ix":10},"p":{"a":1,"k":[{"i":{"x":0.375,"y":1},"o":{"x":0.662,"y":0},"t":4,"s":[123,34.5,0],"e":[123,174.5,0],"to":[0,0,0],"ti":[0,0,0]},{"i":{"x":0.375,"y":1},"o":{"x":0.041,"y":0},"t":10,"s":[123,174.5,0],"e":[123,168.5,0],"to":[0,0,0],"ti":[0,0,0]},{"i":{"x":0.375,"y":1},"o":{"x":0.485,"y":0},"t":15,"s":[123,168.5,0],"e":[123,174.5,0],"to":[0,0,0],"ti":[0,0,0]},{"t":21}],"ix":2,"l":2},"a":{"a":0,"k":[34.5,22.5,0],"ix":1,"l":2},"s":{"a":0,"k":[100,100,100],"ix":6,"l":2}},"ao":0,"ip":1,"op":1112,"st":-11,"bm":0},{"ddd":0,"ind":8,"ty":2,"nm":"阴影2","parent":7,"refId":"image_6","sr":1,"ks":{"o":{"a":0,"k":100,"ix":11},"r":{"a":0,"k":0,"ix":10},"p":{"a":0,"k":[37,36.5,0],"ix":2,"l":2},"a":{"a":0,"k":[33,11.5,0],"ix":1,"l":2},"s":{"a":0,"k":[100,100,100],"ix":6,"l":2}},"ao":0,"ip":1,"op":1112,"st":-11,"bm":0},{"ddd":0,"ind":9,"ty":2,"nm":"金币-下 3","refId":"image_5","sr":1,"ks":{"o":{"a":0,"k":100,"ix":11},"r":{"a":0,"k":0,"ix":10},"p":{"a":1,"k":[{"i":{"x":0.375,"y":1},"o":{"x":0.662,"y":0},"t":3,"s":[127.25,43.5,0],"e":[121.25,199.25,0],"to":[0,0,0],"ti":[0,0,0]},{"i":{"x":0.375,"y":1},"o":{"x":0.105,"y":0},"t":9,"s":[121.25,199.25,0],"e":[124.625,196.75,0],"to":[0,0,0],"ti":[-1.375,0,0]},{"i":{"x":0.375,"y":1},"o":{"x":0.455,"y":0},"t":14,"s":[124.625,196.75,0],"e":[127.25,199.25,0],"to":[1,0,0],"ti":[0,0,0]},{"t":20}],"ix":2,"l":2},"a":{"a":0,"k":[34.5,22.5,0],"ix":1,"l":2},"s":{"a":0,"k":[100,100,100],"ix":6,"l":2}},"ao":0,"ip":1,"op":1112,"st":-11,"bm":0},{"ddd":0,"ind":10,"ty":2,"nm":"阴影1","parent":9,"refId":"image_7","sr":1,"ks":{"o":{"a":0,"k":100,"ix":11},"r":{"a":0,"k":0,"ix":10},"p":{"a":0,"k":[29.75,36.25,0],"ix":2,"l":2},"a":{"a":0,"k":[33,12,0],"ix":1,"l":2},"s":{"a":0,"k":[100,100,100],"ix":6,"l":2}},"ao":0,"ip":1,"op":1112,"st":-11,"bm":0},{"ddd":0,"ind":11,"ty":2,"nm":"金币-下 2","refId":"image_5","sr":1,"ks":{"o":{"a":0,"k":100,"ix":11},"r":{"a":0,"k":0,"ix":10},"p":{"a":1,"k":[{"i":{"x":0.375,"y":1},"o":{"x":0.662,"y":0},"t":1,"s":[121.25,37.5,0],"e":[121.25,223.5,0],"to":[0,0,0],"ti":[0,0,0]},{"t":7}],"ix":2,"l":2},"a":{"a":0,"k":[34.5,22.5,0],"ix":1,"l":2},"s":{"a":0,"k":[100,100,100],"ix":6,"l":2}},"ao":0,"ip":1,"op":1112,"st":-11,"bm":0},{"ddd":0,"ind":12,"ty":2,"nm":"金币上","parent":15,"refId":"image_8","sr":1,"ks":{"o":{"a":0,"k":100,"ix":11},"r":{"a":0,"k":0,"ix":10},"p":{"a":0,"k":[27.5,8.5,0],"ix":2,"l":2},"a":{"a":0,"k":[21.5,6.5,0],"ix":1,"l":2},"s":{"a":0,"k":[100,100,100],"ix":6,"l":2}},"ao":0,"ip":1,"op":1112,"st":-11,"bm":0},{"ddd":0,"ind":13,"ty":2,"nm":"金币下 2","parent":15,"td":1,"refId":"image_9","sr":1,"ks":{"o":{"a":0,"k":100,"ix":11},"r":{"a":0,"k":0,"ix":10},"p":{"a":0,"k":[27.5,18,0],"ix":2,"l":2},"a":{"a":0,"k":[27.5,18,0],"ix":1,"l":2},"s":{"a":0,"k":[100,100,100],"ix":6,"l":2}},"ao":0,"ip":1,"op":1112,"st":-11,"bm":0},{"ddd":0,"ind":14,"ty":2,"nm":"阴影5","parent":15,"tt":1,"tp":13,"refId":"image_10","sr":1,"ks":{"o":{"a":1,"k":[{"i":{"x":[0.667],"y":[1]},"o":{"x":[0.333],"y":[0]},"t":6,"s":[0],"e":[100]},{"t":11}],"ix":11},"r":{"a":0,"k":0,"ix":10},"p":{"a":0,"k":[102,8,0],"ix":2,"l":2},"a":{"a":0,"k":[102,74,0],"ix":1,"l":2},"s":{"a":0,"k":[100,100,100],"ix":6,"l":2}},"ao":0,"hasMask":true,"masksProperties":[{"inv":false,"mode":"a","pt":{"a":0,"k":{"i":[[-6.374,0],[0,10.241],[6.374,0],[0,-10.241]],"o":[[6.374,0],[0,-10.241],[-6.374,0],[0,10.241]],"v":[[21.578,113.26],[33.12,94.717],[21.578,76.175],[10.036,94.717]],"c":true},"ix":1},"o":{"a":0,"k":100,"ix":3},"x":{"a":0,"k":0,"ix":4},"nm":"蒙版 1"}],"ip":1,"op":1112,"st":-11,"bm":0},{"ddd":0,"ind":15,"ty":2,"nm":"金币下","refId":"image_9","sr":1,"ks":{"o":{"a":0,"k":100,"ix":11},"r":{"a":0,"k":0,"ix":10},"p":{"a":1,"k":[{"i":{"x":0.375,"y":1},"o":{"x":0.662,"y":0},"t":-1,"s":[56,79,0],"e":[56,212,0],"to":[0,0,0],"ti":[0,0,0]},{"i":{"x":0.375,"y":1},"o":{"x":0.167,"y":0},"t":5,"s":[56,212,0],"e":[56,210,0],"to":[0,0,0],"ti":[0,0,0]},{"i":{"x":0.375,"y":1},"o":{"x":0.167,"y":0},"t":10,"s":[56,210,0],"e":[56,212,0],"to":[0,0,0],"ti":[0,0,0]},{"t":15}],"ix":2,"l":2},"a":{"a":0,"k":[27.5,18,0],"ix":1,"l":2},"s":{"a":0,"k":[100,100,100],"ix":6,"l":2}},"ao":0,"ip":1,"op":1112,"st":-11,"bm":0}],"markers":[],"props":{}}